{
  "betathome": {
    "odds": [
      {
        "homeTeam": "Costa Rica",
        "awayTeam": "Serbien",
        "forHomeTeam": "5.10",
        "evenGame": "3.30",
        "forAwayTeam": "1.85",
        "link": "https://www.bet-at-home.com/de/sport/fussball/wm-2018-spiele/gruppenphase/costa-rica-serbien-neutraler-spielort/8979237",
        "startAt": 1529236800000
      },
      {
        "homeTeam": "Deutschland",
        "awayTeam": "Mexiko",
        "forHomeTeam": "1.44",
        "evenGame": "4.60",
        "forAwayTeam": "7.80",
        "link": "https://www.bet-at-home.com/de/sport/fussball/wm-2018-spiele/gruppenphase/deutschland-mexiko-neutraler-spielort/8979244",
        "startAt": 1529247600000
      },
      {
        "homeTeam": "Brasilien",
        "awayTeam": "Schweiz",
        "forHomeTeam": "1.42",
        "evenGame": "4.50",
        "forAwayTeam": "8.80",
        "link": "https://www.bet-at-home.com/de/sport/fussball/wm-2018-spiele/gruppenphase/brasilien-schweiz-neutraler-spielort/8979235",
        "startAt": 1529258400000
      },
      {
        "homeTeam": "Schweden",
        "awayTeam": "Südkorea",
        "forHomeTeam": "2.02",
        "evenGame": "3.11",
        "forAwayTeam": "4.12",
        "link": "https://www.bet-at-home.com/de/sport/fussball/wm-2018-spiele/gruppenphase/schweden-sudkorea-neutraler-spielort/8979245",
        "startAt": null
      },
      {
        "homeTeam": "Belgien",
        "awayTeam": "Panama",
        "forHomeTeam": "1.17",
        "evenGame": "6.73",
        "forAwayTeam": "17.99",
        "link": "https://www.bet-at-home.com/de/sport/fussball/wm-2018-spiele/gruppenphase/belgien-panama-neutraler-spielort/8979260",
        "startAt": null
      },
      {
        "homeTeam": "Tunesien",
        "awayTeam": "England",
        "forHomeTeam": "8.41",
        "evenGame": "4.24",
        "forAwayTeam": "1.42",
        "link": "https://www.bet-at-home.com/de/sport/fussball/wm-2018-spiele/gruppenphase/tunesien-england-neutraler-spielort/8979261",
        "startAt": null
      },
      {
        "homeTeam": "Kolumbien",
        "awayTeam": "Japan",
        "forHomeTeam": "1.65",
        "evenGame": "3.66",
        "forAwayTeam": "5.57",
        "link": "https://www.bet-at-home.com/de/sport/fussball/wm-2018-spiele/gruppenphase/kolumbien-japan-neutraler-spielort/8979264",
        "startAt": 1529409600000
      },
      {
        "homeTeam": "Polen",
        "awayTeam": "Senegal",
        "forHomeTeam": "2.34",
        "evenGame": "3.10",
        "forAwayTeam": "3.23",
        "link": "https://www.bet-at-home.com/de/sport/fussball/wm-2018-spiele/gruppenphase/polen-senegal-neutraler-spielort/8979265",
        "startAt": 1529420400000
      },
      {
        "homeTeam": "Russland",
        "awayTeam": "Ägypten",
        "forHomeTeam": "2.16",
        "evenGame": "3.08",
        "forAwayTeam": "3.68",
        "link": "https://www.bet-at-home.com/de/sport/fussball/wm-2018-spiele/gruppenphase/russland-agypten/8979211",
        "startAt": 1529431200000
      },
      {
        "homeTeam": "Portugal",
        "awayTeam": "Marokko",
        "forHomeTeam": "1.57",
        "evenGame": "3.87",
        "forAwayTeam": "6.10",
        "link": "https://www.bet-at-home.com/de/sport/fussball/wm-2018-spiele/gruppenphase/portugal-marokko-neutraler-spielort/8979223",
        "startAt": 1529496000000
      },
      {
        "homeTeam": "Uruguay",
        "awayTeam": "Saudi-Arabien",
        "forHomeTeam": "1.15",
        "evenGame": "7.33",
        "forAwayTeam": "17.78",
        "link": "https://www.bet-at-home.com/de/sport/fussball/wm-2018-spiele/gruppenphase/uruguay-saudi-arabien-neutraler-spielort/8979216",
        "startAt": 1529506800000
      },
      {
        "homeTeam": "Iran",
        "awayTeam": "Spanien",
        "forHomeTeam": "22.18",
        "evenGame": "7.03",
        "forAwayTeam": "1.15",
        "link": "https://www.bet-at-home.com/de/sport/fussball/wm-2018-spiele/gruppenphase/iran-spanien-neutraler-spielort/8979221",
        "startAt": 1529517600000
      },
      {
        "homeTeam": "Dänemark",
        "awayTeam": "Australien",
        "forHomeTeam": "1.83",
        "evenGame": "3.40",
        "forAwayTeam": "4.56",
        "link": "https://www.bet-at-home.com/de/sport/fussball/wm-2018-spiele/gruppenphase/danemark-australien-neutraler-spielort/8979226",
        "startAt": 1529582400000
      },
      {
        "homeTeam": "Frankreich",
        "awayTeam": "Peru",
        "forHomeTeam": "1.50",
        "evenGame": "4.20",
        "forAwayTeam": "6.43",
        "link": "https://www.bet-at-home.com/de/sport/fussball/wm-2018-spiele/gruppenphase/frankreich-peru-neutraler-spielort/8979227",
        "startAt": 1529593200000
      },
      {
        "homeTeam": "Argentinien",
        "awayTeam": "Kroatien",
        "forHomeTeam": "1.97",
        "evenGame": "3.28",
        "forAwayTeam": "4.03",
        "link": "https://www.bet-at-home.com/de/sport/fussball/wm-2018-spiele/gruppenphase/argentinien-kroatien-neutraler-spielort/8979228",
        "startAt": 1529604000000
      },
      {
        "homeTeam": "Brasilien",
        "awayTeam": "Costa",
        "forHomeTeam": "1.19",
        "evenGame": "6.26",
        "forAwayTeam": "17.29",
        "link": "https://www.bet-at-home.com/de/sport/fussball/wm-2018-spiele/gruppenphase/brasilien-costa-rica-neutraler-spielort/8979238",
        "startAt": 1529668800000
      },
      {
        "homeTeam": "Nigeria",
        "awayTeam": "Island",
        "forHomeTeam": "2.91",
        "evenGame": "3.02",
        "forAwayTeam": "2.59",
        "link": "https://www.bet-at-home.com/de/sport/fussball/wm-2018-spiele/gruppenphase/nigeria-island-neutraler-spielort/8979229",
        "startAt": 1529679600000
      },
      {
        "homeTeam": "Serbien",
        "awayTeam": "Schweiz",
        "forHomeTeam": "2.87",
        "evenGame": "3.06",
        "forAwayTeam": "2.60",
        "link": "https://www.bet-at-home.com/de/sport/fussball/wm-2018-spiele/gruppenphase/serbien-schweiz-neutraler-spielort/8979236",
        "startAt": 1529690400000
      },
      {
        "homeTeam": "Belgien",
        "awayTeam": "Tunesien",
        "forHomeTeam": "1.33",
        "evenGame": "5.00",
        "forAwayTeam": "9.19",
        "link": "https://www.bet-at-home.com/de/sport/fussball/wm-2018-spiele/gruppenphase/belgien-tunesien-neutraler-spielort/8979249",
        "startAt": 1529755200000
      },
      {
        "homeTeam": "Südkorea",
        "awayTeam": "Mexiko",
        "forHomeTeam": "4.97",
        "evenGame": "3.50",
        "forAwayTeam": "1.74",
        "link": "https://www.bet-at-home.com/de/sport/fussball/wm-2018-spiele/gruppenphase/sudkorea-mexiko-neutraler-spielort/8979269",
        "startAt": 1529766000000
      },
      {
        "homeTeam": "Deutschland",
        "awayTeam": "Schweden",
        "forHomeTeam": "1.39",
        "evenGame": "4.60",
        "forAwayTeam": "8.22",
        "link": "https://www.bet-at-home.com/de/sport/fussball/wm-2018-spiele/gruppenphase/deutschland-schweden-neutraler-spielort/8979241",
        "startAt": 1529776800000
      },
      {
        "homeTeam": "England",
        "awayTeam": "Panama",
        "forHomeTeam": "1.19",
        "evenGame": "6.13",
        "forAwayTeam": "17.29",
        "link": "https://www.bet-at-home.com/de/sport/fussball/wm-2018-spiele/gruppenphase/england-panama-neutraler-spielort/8979250",
        "startAt": 1529841600000
      },
      {
        "homeTeam": "Japan",
        "awayTeam": "Senegal",
        "forHomeTeam": "3.60",
        "evenGame": "3.23",
        "forAwayTeam": "2.12",
        "link": "https://www.bet-at-home.com/de/sport/fussball/wm-2018-spiele/gruppenphase/japan-senegal-neutraler-spielort/8979263",
        "startAt": 1529852400000
      },
      {
        "homeTeam": "Polen",
        "awayTeam": "Kolumbien",
        "forHomeTeam": "3.33",
        "evenGame": "3.21",
        "forAwayTeam": "2.23",
        "link": "https://www.bet-at-home.com/de/sport/fussball/wm-2018-spiele/gruppenphase/polen-kolumbien-neutraler-spielort/8979262",
        "startAt": 1529863200000
      },
      {
        "homeTeam": "Saudi-Arabien",
        "awayTeam": "Ägypten",
        "forHomeTeam": "7.31",
        "evenGame": "4.21",
        "forAwayTeam": "1.46",
        "link": "https://www.bet-at-home.com/de/sport/fussball/wm-2018-spiele/gruppenphase/saudi-arabien-agypten-neutraler-spielort/8979218",
        "startAt": 1529935200000
      },
      {
        "homeTeam": "Uruguay",
        "awayTeam": "Russland",
        "forHomeTeam": "2.25",
        "evenGame": "3.14",
        "forAwayTeam": "3.37",
        "link": "https://www.bet-at-home.com/de/sport/fussball/wm-2018-spiele/gruppenphase/uruguay-russland-neutraler-spielort/8979219",
        "startAt": 1529935200000
      },
      {
        "homeTeam": "Spanien",
        "awayTeam": "Marokko",
        "forHomeTeam": "1.34",
        "evenGame": "4.91",
        "forAwayTeam": "8.97",
        "link": "https://www.bet-at-home.com/de/sport/fussball/wm-2018-spiele/gruppenphase/spanien-marokko-neutraler-spielort/8979213",
        "startAt": 1529949600000
      },
      {
        "homeTeam": "Iran",
        "awayTeam": "Portugal",
        "forHomeTeam": "9.99",
        "evenGame": "4.87",
        "forAwayTeam": "1.32",
        "link": "https://www.bet-at-home.com/de/sport/fussball/wm-2018-spiele/gruppenphase/iran-portugal-neutraler-spielort/8979215",
        "startAt": 1529949600000
      },
      {
        "homeTeam": "Dänemark",
        "awayTeam": "Frankreich",
        "forHomeTeam": "4.76",
        "evenGame": "3.62",
        "forAwayTeam": "1.74",
        "link": "https://www.bet-at-home.com/de/sport/fussball/wm-2018-spiele/gruppenphase/danemark-frankreich-neutraler-spielort/8979225",
        "startAt": 1530021600000
      },
      {
        "homeTeam": "Australien",
        "awayTeam": "Peru",
        "forHomeTeam": "3.71",
        "evenGame": "3.31",
        "forAwayTeam": "2.05",
        "link": "https://www.bet-at-home.com/de/sport/fussball/wm-2018-spiele/gruppenphase/australien-peru-neutraler-spielort/8979230",
        "startAt": 1530021600000
      },
      {
        "homeTeam": "Nigeria",
        "awayTeam": "Argentinien",
        "forHomeTeam": "8.66",
        "evenGame": "4.97",
        "forAwayTeam": "1.35",
        "link": "https://www.bet-at-home.com/de/sport/fussball/wm-2018-spiele/gruppenphase/nigeria-argentinien-neutraler-spielort/8979231",
        "startAt": 1530036000000
      },
      {
        "homeTeam": "Island",
        "awayTeam": "Kroatien",
        "forHomeTeam": "4.59",
        "evenGame": "3.47",
        "forAwayTeam": "1.81",
        "link": "https://www.bet-at-home.com/de/sport/fussball/wm-2018-spiele/gruppenphase/island-kroatien-neutraler-spielort/8979233",
        "startAt": 1530036000000
      },
      {
        "homeTeam": "Mexiko",
        "awayTeam": "Schweden",
        "forHomeTeam": "2.44",
        "evenGame": "3.12",
        "forAwayTeam": "3.03",
        "link": "https://www.bet-at-home.com/de/sport/fussball/wm-2018-spiele/gruppenphase/mexiko-schweden-neutraler-spielort/8979242",
        "startAt": 1530108000000
      },
      {
        "homeTeam": "Südkorea",
        "awayTeam": "Deutschland",
        "forHomeTeam": "10.76",
        "evenGame": "5.66",
        "forAwayTeam": "1.27",
        "link": "https://www.bet-at-home.com/de/sport/fussball/wm-2018-spiele/gruppenphase/sudkorea-deutschland-neutraler-spielort/8979268",
        "startAt": 1530108000000
      },
      {
        "homeTeam": "Serbien",
        "awayTeam": "Brasilien",
        "forHomeTeam": "8.42",
        "evenGame": "4.66",
        "forAwayTeam": "1.38",
        "link": "https://www.bet-at-home.com/de/sport/fussball/wm-2018-spiele/gruppenphase/serbien-brasilien-neutraler-spielort/8979239",
        "startAt": 1530122400000
      },
      {
        "homeTeam": "Schweiz",
        "awayTeam": "Costa",
        "forHomeTeam": "1.87",
        "evenGame": "3.31",
        "forAwayTeam": "4.48",
        "link": "https://www.bet-at-home.com/de/sport/fussball/wm-2018-spiele/gruppenphase/schweiz-costa-rica-neutraler-spielort/8979240",
        "startAt": 1530122400000
      },
      {
        "homeTeam": "Japan",
        "awayTeam": "Polen",
        "forHomeTeam": "4.28",
        "evenGame": "3.49",
        "forAwayTeam": "1.85",
        "link": "https://www.bet-at-home.com/de/sport/fussball/wm-2018-spiele/gruppenphase/japan-polen-neutraler-spielort/8979266",
        "startAt": 1530194400000
      },
      {
        "homeTeam": "Senegal",
        "awayTeam": "Kolumbien",
        "forHomeTeam": "3.85",
        "evenGame": "3.28",
        "forAwayTeam": "2.02",
        "link": "https://www.bet-at-home.com/de/sport/fussball/wm-2018-spiele/gruppenphase/senegal-kolumbien-neutraler-spielort/8979267",
        "startAt": 1530194400000
      },
      {
        "homeTeam": "England",
        "awayTeam": "Belgien",
        "forHomeTeam": "2.89",
        "evenGame": "3.32",
        "forAwayTeam": "2.43",
        "link": "https://www.bet-at-home.com/de/sport/fussball/wm-2018-spiele/gruppenphase/england-belgien-neutraler-spielort/8979247",
        "startAt": 1530208800000
      },
      {
        "homeTeam": "Panama",
        "awayTeam": "Tunesien",
        "forHomeTeam": "3.66",
        "evenGame": "3.23",
        "forAwayTeam": "2.10",
        "link": "https://www.bet-at-home.com/de/sport/fussball/wm-2018-spiele/gruppenphase/panama-tunesien-neutraler-spielort/8979248",
        "startAt": 1530208800000
      }
    ],
    "minedAt": 1529233064763
  }
}