{
  "betathome": {
    "odds": [
      {
        "homeTeam": "Kolumbien",
        "awayTeam": "Japan",
        "forHomeTeam": "1.78",
        "evenGame": "3.35",
        "forAwayTeam": "5.50",
        "link": "https://www.bet-at-home.com/de/sport/fussball/wm-2018-spiele/gruppenphase/kolumbien-japan-neutraler-spielort/8979264",
        "startAt": 1529409600000
      },
      {
        "homeTeam": "Polen",
        "awayTeam": "Senegal",
        "forHomeTeam": "2.30",
        "evenGame": "3.10",
        "forAwayTeam": "3.55",
        "link": "https://www.bet-at-home.com/de/sport/fussball/wm-2018-spiele/gruppenphase/polen-senegal-neutraler-spielort/8979265",
        "startAt": 1529420400000
      },
      {
        "homeTeam": "Russland",
        "awayTeam": "Ägypten",
        "forHomeTeam": "2.10",
        "evenGame": "3.10",
        "forAwayTeam": "4.15",
        "link": "https://www.bet-at-home.com/de/sport/fussball/wm-2018-spiele/gruppenphase/russland-agypten/8979211",
        "startAt": 1529431200000
      },
      {
        "homeTeam": "Portugal",
        "awayTeam": "Marokko",
        "forHomeTeam": "1.64",
        "evenGame": "3.68",
        "forAwayTeam": "5.63",
        "link": "https://www.bet-at-home.com/de/sport/fussball/wm-2018-spiele/gruppenphase/portugal-marokko-neutraler-spielort/8979223",
        "startAt": null
      },
      {
        "homeTeam": "Uruguay",
        "awayTeam": "Saudi-Arabien",
        "forHomeTeam": "1.16",
        "evenGame": "6.98",
        "forAwayTeam": "17.44",
        "link": "https://www.bet-at-home.com/de/sport/fussball/wm-2018-spiele/gruppenphase/uruguay-saudi-arabien-neutraler-spielort/8979216",
        "startAt": null
      },
      {
        "homeTeam": "Iran",
        "awayTeam": "Spanien",
        "forHomeTeam": "19.00",
        "evenGame": "6.50",
        "forAwayTeam": "1.17",
        "link": "https://www.bet-at-home.com/de/sport/fussball/wm-2018-spiele/gruppenphase/iran-spanien-neutraler-spielort/8979221",
        "startAt": null
      },
      {
        "homeTeam": "Dänemark",
        "awayTeam": "Australien",
        "forHomeTeam": "1.90",
        "evenGame": "3.25",
        "forAwayTeam": "4.40",
        "link": "https://www.bet-at-home.com/de/sport/fussball/wm-2018-spiele/gruppenphase/danemark-australien-neutraler-spielort/8979226",
        "startAt": 1529582400000
      },
      {
        "homeTeam": "Frankreich",
        "awayTeam": "Peru",
        "forHomeTeam": "1.54",
        "evenGame": "3.99",
        "forAwayTeam": "6.19",
        "link": "https://www.bet-at-home.com/de/sport/fussball/wm-2018-spiele/gruppenphase/frankreich-peru-neutraler-spielort/8979227",
        "startAt": 1529593200000
      },
      {
        "homeTeam": "Argentinien",
        "awayTeam": "Kroatien",
        "forHomeTeam": "1.98",
        "evenGame": "3.27",
        "forAwayTeam": "4.01",
        "link": "https://www.bet-at-home.com/de/sport/fussball/wm-2018-spiele/gruppenphase/argentinien-kroatien-neutraler-spielort/8979228",
        "startAt": 1529604000000
      },
      {
        "homeTeam": "Brasilien",
        "awayTeam": "Costa",
        "forHomeTeam": "1.19",
        "evenGame": "6.43",
        "forAwayTeam": "16.28",
        "link": "https://www.bet-at-home.com/de/sport/fussball/wm-2018-spiele/gruppenphase/brasilien-costa-rica-neutraler-spielort/8979238",
        "startAt": 1529668800000
      },
      {
        "homeTeam": "Nigeria",
        "awayTeam": "Island",
        "forHomeTeam": "2.92",
        "evenGame": "2.98",
        "forAwayTeam": "2.62",
        "link": "https://www.bet-at-home.com/de/sport/fussball/wm-2018-spiele/gruppenphase/nigeria-island-neutraler-spielort/8979229",
        "startAt": 1529679600000
      },
      {
        "homeTeam": "Serbien",
        "awayTeam": "Schweiz",
        "forHomeTeam": "3.01",
        "evenGame": "2.97",
        "forAwayTeam": "2.56",
        "link": "https://www.bet-at-home.com/de/sport/fussball/wm-2018-spiele/gruppenphase/serbien-schweiz-neutraler-spielort/8979236",
        "startAt": 1529690400000
      },
      {
        "homeTeam": "Belgien",
        "awayTeam": "Tunesien",
        "forHomeTeam": "1.32",
        "evenGame": "5.13",
        "forAwayTeam": "9.41",
        "link": "https://www.bet-at-home.com/de/sport/fussball/wm-2018-spiele/gruppenphase/belgien-tunesien-neutraler-spielort/8979249",
        "startAt": 1529755200000
      },
      {
        "homeTeam": "Südkorea",
        "awayTeam": "Mexiko",
        "forHomeTeam": "6.26",
        "evenGame": "3.85",
        "forAwayTeam": "1.56",
        "link": "https://www.bet-at-home.com/de/sport/fussball/wm-2018-spiele/gruppenphase/sudkorea-mexiko-neutraler-spielort/8979269",
        "startAt": 1529766000000
      },
      {
        "homeTeam": "Deutschland",
        "awayTeam": "Schweden",
        "forHomeTeam": "1.43",
        "evenGame": "4.45",
        "forAwayTeam": "7.38",
        "link": "https://www.bet-at-home.com/de/sport/fussball/wm-2018-spiele/gruppenphase/deutschland-schweden-neutraler-spielort/8979241",
        "startAt": 1529776800000
      },
      {
        "homeTeam": "England",
        "awayTeam": "Panama",
        "forHomeTeam": "1.19",
        "evenGame": "6.21",
        "forAwayTeam": "17.65",
        "link": "https://www.bet-at-home.com/de/sport/fussball/wm-2018-spiele/gruppenphase/england-panama-neutraler-spielort/8979250",
        "startAt": 1529841600000
      },
      {
        "homeTeam": "Japan",
        "awayTeam": "Senegal",
        "forHomeTeam": "3.58",
        "evenGame": "3.25",
        "forAwayTeam": "2.11",
        "link": "https://www.bet-at-home.com/de/sport/fussball/wm-2018-spiele/gruppenphase/japan-senegal-neutraler-spielort/8979263",
        "startAt": 1529852400000
      },
      {
        "homeTeam": "Polen",
        "awayTeam": "Kolumbien",
        "forHomeTeam": "3.31",
        "evenGame": "3.18",
        "forAwayTeam": "2.26",
        "link": "https://www.bet-at-home.com/de/sport/fussball/wm-2018-spiele/gruppenphase/polen-kolumbien-neutraler-spielort/8979262",
        "startAt": 1529863200000
      },
      {
        "homeTeam": "Saudi-Arabien",
        "awayTeam": "Ägypten",
        "forHomeTeam": "7.20",
        "evenGame": "4.31",
        "forAwayTeam": "1.45",
        "link": "https://www.bet-at-home.com/de/sport/fussball/wm-2018-spiele/gruppenphase/saudi-arabien-agypten-neutraler-spielort/8979218",
        "startAt": 1529935200000
      },
      {
        "homeTeam": "Uruguay",
        "awayTeam": "Russland",
        "forHomeTeam": "2.28",
        "evenGame": "3.13",
        "forAwayTeam": "3.32",
        "link": "https://www.bet-at-home.com/de/sport/fussball/wm-2018-spiele/gruppenphase/uruguay-russland-neutraler-spielort/8979219",
        "startAt": 1529935200000
      },
      {
        "homeTeam": "Spanien",
        "awayTeam": "Marokko",
        "forHomeTeam": "1.33",
        "evenGame": "5.05",
        "forAwayTeam": "9.18",
        "link": "https://www.bet-at-home.com/de/sport/fussball/wm-2018-spiele/gruppenphase/spanien-marokko-neutraler-spielort/8979213",
        "startAt": 1529949600000
      },
      {
        "homeTeam": "Iran",
        "awayTeam": "Portugal",
        "forHomeTeam": "9.47",
        "evenGame": "4.79",
        "forAwayTeam": "1.34",
        "link": "https://www.bet-at-home.com/de/sport/fussball/wm-2018-spiele/gruppenphase/iran-portugal-neutraler-spielort/8979215",
        "startAt": 1529949600000
      },
      {
        "homeTeam": "Dänemark",
        "awayTeam": "Frankreich",
        "forHomeTeam": "5.02",
        "evenGame": "3.68",
        "forAwayTeam": "1.70",
        "link": "https://www.bet-at-home.com/de/sport/fussball/wm-2018-spiele/gruppenphase/danemark-frankreich-neutraler-spielort/8979225",
        "startAt": 1530021600000
      },
      {
        "homeTeam": "Australien",
        "awayTeam": "Peru",
        "forHomeTeam": "3.53",
        "evenGame": "3.31",
        "forAwayTeam": "2.11",
        "link": "https://www.bet-at-home.com/de/sport/fussball/wm-2018-spiele/gruppenphase/australien-peru-neutraler-spielort/8979230",
        "startAt": 1530021600000
      },
      {
        "homeTeam": "Nigeria",
        "awayTeam": "Argentinien",
        "forHomeTeam": "9.13",
        "evenGame": "5.09",
        "forAwayTeam": "1.33",
        "link": "https://www.bet-at-home.com/de/sport/fussball/wm-2018-spiele/gruppenphase/nigeria-argentinien-neutraler-spielort/8979231",
        "startAt": 1530036000000
      },
      {
        "homeTeam": "Island",
        "awayTeam": "Kroatien",
        "forHomeTeam": "4.77",
        "evenGame": "3.50",
        "forAwayTeam": "1.77",
        "link": "https://www.bet-at-home.com/de/sport/fussball/wm-2018-spiele/gruppenphase/island-kroatien-neutraler-spielort/8979233",
        "startAt": 1530036000000
      },
      {
        "homeTeam": "Mexiko",
        "awayTeam": "Schweden",
        "forHomeTeam": "2.15",
        "evenGame": "3.20",
        "forAwayTeam": "3.50",
        "link": "https://www.bet-at-home.com/de/sport/fussball/wm-2018-spiele/gruppenphase/mexiko-schweden-neutraler-spielort/8979242",
        "startAt": 1530108000000
      },
      {
        "homeTeam": "Südkorea",
        "awayTeam": "Deutschland",
        "forHomeTeam": "14.18",
        "evenGame": "6.59",
        "forAwayTeam": "1.19",
        "link": "https://www.bet-at-home.com/de/sport/fussball/wm-2018-spiele/gruppenphase/sudkorea-deutschland-neutraler-spielort/8979268",
        "startAt": 1530108000000
      },
      {
        "homeTeam": "Serbien",
        "awayTeam": "Brasilien",
        "forHomeTeam": "7.72",
        "evenGame": "4.55",
        "forAwayTeam": "1.41",
        "link": "https://www.bet-at-home.com/de/sport/fussball/wm-2018-spiele/gruppenphase/serbien-brasilien-neutraler-spielort/8979239",
        "startAt": 1530122400000
      },
      {
        "homeTeam": "Schweiz",
        "awayTeam": "Costa",
        "forHomeTeam": "1.73",
        "evenGame": "3.42",
        "forAwayTeam": "5.28",
        "link": "https://www.bet-at-home.com/de/sport/fussball/wm-2018-spiele/gruppenphase/schweiz-costa-rica-neutraler-spielort/8979240",
        "startAt": 1530122400000
      },
      {
        "homeTeam": "Japan",
        "awayTeam": "Polen",
        "forHomeTeam": "4.28",
        "evenGame": "3.49",
        "forAwayTeam": "1.85",
        "link": "https://www.bet-at-home.com/de/sport/fussball/wm-2018-spiele/gruppenphase/japan-polen-neutraler-spielort/8979266",
        "startAt": 1530194400000
      },
      {
        "homeTeam": "Senegal",
        "awayTeam": "Kolumbien",
        "forHomeTeam": "3.85",
        "evenGame": "3.28",
        "forAwayTeam": "2.02",
        "link": "https://www.bet-at-home.com/de/sport/fussball/wm-2018-spiele/gruppenphase/senegal-kolumbien-neutraler-spielort/8979267",
        "startAt": 1530194400000
      },
      {
        "homeTeam": "England",
        "awayTeam": "Belgien",
        "forHomeTeam": "2.88",
        "evenGame": "3.29",
        "forAwayTeam": "2.44",
        "link": "https://www.bet-at-home.com/de/sport/fussball/wm-2018-spiele/gruppenphase/england-belgien-neutraler-spielort/8979247",
        "startAt": 1530208800000
      },
      {
        "homeTeam": "Panama",
        "awayTeam": "Tunesien",
        "forHomeTeam": "3.97",
        "evenGame": "3.28",
        "forAwayTeam": "1.99",
        "link": "https://www.bet-at-home.com/de/sport/fussball/wm-2018-spiele/gruppenphase/panama-tunesien-neutraler-spielort/8979248",
        "startAt": 1530208800000
      }
    ],
    "minedAt": 1529404032393
  }
}